README.rst
setup.cfg
setup.py
magnetsdk2/__init__.py
magnetsdk2/cef.py
magnetsdk2/cli.py
magnetsdk2/connection.py
magnetsdk2/csv.py
magnetsdk2/iterator.py
magnetsdk2/time.py
magnetsdk2/validation.py
magnetsdk2.egg-info/PKG-INFO
magnetsdk2.egg-info/SOURCES.txt
magnetsdk2.egg-info/dependency_links.txt
magnetsdk2.egg-info/entry_points.txt
magnetsdk2.egg-info/requires.txt
magnetsdk2.egg-info/top_level.txt